odoo8_addon_intrastat_base-8.0.1.3.0.99.dev13-py2.7-nspkg.pth
odoo8_addon_intrastat_base-8.0.1.3.0.99.dev13.dist-info/METADATA
odoo8_addon_intrastat_base-8.0.1.3.0.99.dev13.dist-info/RECORD
odoo8_addon_intrastat_base-8.0.1.3.0.99.dev13.dist-info/WHEEL
odoo8_addon_intrastat_base-8.0.1.3.0.99.dev13.dist-info/namespace_packages.txt
odoo8_addon_intrastat_base-8.0.1.3.0.99.dev13.dist-info/top_level.txt
odoo_addons/intrastat_base/README.rst
odoo_addons/intrastat_base/__init__.py
odoo_addons/intrastat_base/__openerp__.py
odoo_addons/intrastat_base/data/country_data.xml
odoo_addons/intrastat_base/demo/intrastat_demo.xml
odoo_addons/intrastat_base/i18n/intrastat_base.pot
odoo_addons/intrastat_base/models/__init__.py
odoo_addons/intrastat_base/models/account_tax.py
odoo_addons/intrastat_base/models/intrastat_common.py
odoo_addons/intrastat_base/models/product_template.py
odoo_addons/intrastat_base/models/res_company.py
odoo_addons/intrastat_base/models/res_country.py
odoo_addons/intrastat_base/static/description/icon.png
odoo_addons/intrastat_base/tests/__init__.py
odoo_addons/intrastat_base/tests/test_all.py
odoo_addons/intrastat_base/views/account_tax.xml
odoo_addons/intrastat_base/views/intrastat.xml
odoo_addons/intrastat_base/views/product_template.xml
odoo_addons/intrastat_base/views/res_company.xml
odoo_addons/intrastat_base/views/res_country.xml
odoo_addons/intrastat_base/views/res_partner.xml
